LICENSE.txt
MANIFEST.in
README.rst
setup.cfg
setup.py
source/conf.py
source/index.rst
src/glassbox/__init__.py
src/glassbox/compat.py
src/glassbox/extension.c
src/glassbox/extension.pyx
src/glassbox/implementation.py
src/glassbox/novelty.py
src/glassbox/pure.py
src/glassbox/record.py
src/glassbox.egg-info/PKG-INFO
src/glassbox.egg-info/SOURCES.txt
src/glassbox.egg-info/dependency_links.txt
src/glassbox.egg-info/top_level.txt
src/glassbox.egg-info/zip-safe
tests/test_implementation.py
tests/test_records.py
tests/test_tracking.py